pytest_pypi/__init__.py
pytest_pypi/app.py
pytest_pypi/certs.py
pytest_pypi/plugin.py
pytest_pypi/serve.py
pytest_pypi/version.py
pytest_pypi-0.1.1.dist-info/DESCRIPTION.rst
pytest_pypi-0.1.1.dist-info/METADATA
pytest_pypi-0.1.1.dist-info/RECORD
pytest_pypi-0.1.1.dist-info/WHEEL
pytest_pypi-0.1.1.dist-info/entry_points.txt
pytest_pypi-0.1.1.dist-info/metadata.json
pytest_pypi-0.1.1.dist-info/top_level.txt
