Metadata-Version: 2.0
Name: pytest-pypi
Version: 0.1.1
Summary: Easily test your HTTP library against a local copy of pypi
Home-page: https://github.com/kennethreitz/pytest-pypi
Author: Kenneth Reitz
Author-email: me@kennethreitz.org
License: MIT
Keywords: pytest-pypi testing pytest pypi
Platform: UNKNOWN
Classifier: Development Status :: 3 - Alpha
Classifier: Intended Audience :: Developers
Classifier: Topic :: Software Development :: Testing
Classifier: Topic :: Software Development :: Libraries
Classifier: License :: OSI Approved :: MIT License
Classifier: Programming Language :: Python :: 2
Classifier: Programming Language :: Python :: 2.6
Classifier: Programming Language :: Python :: 2.7
Classifier: Programming Language :: Python :: 3
Classifier: Programming Language :: Python :: 3.4
Classifier: Programming Language :: Python :: 3.5
Classifier: Programming Language :: Python :: 3.6
Requires-Dist: Flask
Requires-Dist: six
